rest_serializer_to_typescript/__init__.py
rest_serializer_to_typescript/apps.py
rest_serializer_to_typescript/main.py
rest_serializer_to_typescript/management/__init__.py
rest_serializer_to_typescript/management/commands/__init__.py
rest_serializer_to_typescript/management/commands/serializer_to_ts.py
rest_serializer_to_typescript/mapping.py
rest_serializer_to_typescript/metadata.py
rest_serializer_to_typescript/models.py
rest_serializer_to_typescript/schema_generator.py
rest_serializer_to_typescript/tests/__init__.py
rest_serializer_to_typescript/tests/schema.py
rest_serializer_to_typescript/tests/transpiler.py
rest_serializer_to_typescript/type_hinting_mapping.py
rest_serializer_to_typescript-0.2.4.dist-info/LICENSE
rest_serializer_to_typescript-0.2.4.dist-info/WHEEL
rest_serializer_to_typescript-0.2.4.dist-info/METADATA
rest_serializer_to_typescript-0.2.4.dist-info/RECORD
