Metadata-Version: 2.1
Name: rest-serializer-to-typescript
Version: 0.2.4
Summary: 
License: MIT
Author: Abdollah Keshtkar
Author-email: hamadkeshtkar@gmail.com
Requires-Python: >=3.9,<4.0
Classifier: License :: OSI Approved :: MIT License
Classifier: Programming Language :: Python :: 3
Classifier: Programming Language :: Python :: 3.10
Classifier: Programming Language :: Python :: 3.9
Requires-Dist: djangorestframework (>=3.12.4,<4.0.0)
